poetry_demo_wb/__init__.py
poetry_demo_wb/console.py
poetry_demo_wb-0.1.2.dist-info/entry_points.txt
poetry_demo_wb-0.1.2.dist-info/WHEEL
poetry_demo_wb-0.1.2.dist-info/METADATA
poetry_demo_wb-0.1.2.dist-info/RECORD
